outplan/__init__.py
outplan/client.py
outplan/const.py
outplan/exceptions.py
outplan/experiment.py
outplan/local.py
outplan-3.0.1.dist-info/LICENSE
outplan-3.0.1.dist-info/METADATA
outplan-3.0.1.dist-info/WHEEL
outplan-3.0.1.dist-info/top_level.txt
outplan-3.0.1.dist-info/RECORD
