Metadata-Version: 2.1
Name: outplan
Version: 3.0.1
Summary: Support nested experiment/namespace base on Facebook Planout
Author-email: x1ah <gaoxiaoqiang@xiachufang.com>
License: MIT License
Project-URL: Repository, https://github.com/xiachufang/outplan
Classifier: Development Status :: 5 - Production/Stable
Classifier: License :: OSI Approved :: MIT License
Classifier: Natural Language :: Chinese (Simplified)
Classifier: Programming Language :: Python :: 3
Classifier: Programming Language :: Python :: 3.7
Classifier: Programming Language :: Python :: 3.8
Classifier: Programming Language :: Python :: 3.9
Requires-Python: >=3.6
License-File: LICENSE
Requires-Dist: planout ==0.6.0
Requires-Dist: six
Requires-Dist: typing-extensions
Provides-Extra: test
Requires-Dist: pytest ; extra == 'test'
Requires-Dist: gevent ; extra == 'test'
